[
  {
    "hadith_id": "2660",
    "hadith": "سُئِلَ رَسُولُ اللهِ صَلَّى اللَّهُ عليه وَسَلَّمَ، عن أَطْفَالِ المُشْرِكِينَ؟ قالَ: اللَّهُ أَعْلَمُ بما كَانُوا عَامِلِينَ إذْ خَلَقَهُمْ.",
    "rawi": "عبدالله بن عباس",
    "mohdith": "مسلم",
    "book": "صحيح مسلم",
    "numberOrPage": "2660",
    "grade": "[صحيح]",
    "takhrij": "أخرجه البخاري (1383) باختلاف يسير",
    "sharh": "خَلَقَ الله سبحانه كُلَّ شيءٍ وقَدَّرَه وكَتَبه عِندَه، وقَدَّرَ للجَنَّةِ أهْلَها، وللنَّارِ أهْلَها، ورُبَّما أَشكَلَ على الصَّحابةِ رِضوانُ اللهِ عليهم مسائِلُ؛ فيَرجِعونَ بها على النبيِّ صلَّى اللهُ عليه وسلَّمَ ليُفتيَهم.\r\nوفي هذا الحديثِ يُخبِرُ عبدُ الله بنُ عبَّاسٍ رَضيَ اللهُ عنهما أنَّ رسولَ الله صلَّى اللهُ عليه وسلَّمَ سُئل عن أولادُ المشركينَ الَّذين ماتوا في صِغَرِهم قبْلَ أنْ يَبلغوا ويَجريَ عليهمُ القلَمُ: هل يَدخلونَ الجنَّةَ أمْ لا؟ فأجاب بأنَّ الله يَعلَمُ حينَ خلَقَهم لو بلَغوا وكَبِروا كيْفَ كانوا سيَعملون، هلْ يُسْلِمونَ أمْ يَكونونَ على دِينِ آبائِهم، فيُجازِيهم بما عَلِم أنَّهُم كانوا سيَفعَلونه لو عاشُوا. وقيل: معناه أنَّ أمْرَهم مُفَوَّضٌ إلى عِلمِ اللهِ تعالَى بحسَبِ عِلمِه بما كانوا عامِلينَ.\r\nوقولُه في هذا الحَديثِ: «اللهُ أعلَمُ بما كانوا عامِلينَ» لا يَتنافَى مع القَولِ بامتِحانِ أطْفالِ المشركينَ يومَ القِيامةِ، ويُمكِنُ جُعْلُه دَليلًا على الامتحانِ؛ لأنَّ اللهَ يَعلَمُ ما كانوا عامِلينَ، أي: إنْ نجَحوا وآمَنوا ساعةَ الامتحانِ يومَ القِيامةِ فاللهُ تعالَى سيُدخِلُهمُ الجنَّةَ، وإنْ كفَروا وعَصَوُا اللهَ تعالَى سيُدخِلُهمُ النَّارَ. وذهَبَ بَعضُ أهلِ العِلمِ إلى أنَّ أطفالَ المشركينَ في الجنَّةِ؛ لقولِه صلَّى اللهُ عليه وسلَّمَ في الحديثِ المتَّفَقِ عليه: «كلُّ مَولودٍ يُولَدُ على الفِطرةِ»، وذهب بعضُهم إلى التوقُّفِ في الحُكمِ على أطْفالِ المشرِكينَ، وفي المسألةِ خِلافٌ مشهورٌ، والعِلمُ عِندَ اللهِ تعالَى.",
    "hadith_lessons": [
      "يُستَفادُ مِنَ الحَدِيثِ'سُئِلَ رَسُولُ اللهِ صَلَّى اللَّهُ عليه وَسَلَّمَ، عن أَطْفَالِ المُشْرِكِينَ؟ قالَ: اللَّهُ أَعْلَمُ بما كَانُوا عَامِلِينَ إذْ خَلَقَهُمْ.' أَنَّ أَمْرَ أَطْفَالِ المُشْرِكِينَ مَوْكُولٌ إِلَى عِلْمِ اللهِ تَعَالَى، وَأَنَّهُ سُبْحَانَهُ يَعْلَمُ مَا كَانُوا سَيَفْعَلُونَ لَوْ بَلَغُوا، وَيُجَازِيهِمْ بِحَسَبِ ذَلِكَ. وَفِيهِ تَذْكِيرٌ بِأَهَمِّيَّةِ التَّوَكُّلِ عَلَى حِكْمَةِ اللهِ وَعَدْلِهِ، وَأَنَّ العِلْمَ بِمَصِيرِهِمْ مَحْجُوبٌ عَنَّا، فَنَتَوَقَّفُ فِي الحُكْمِ عَلَيْهِمْ وَنُفَوِّضُ أَمْرَهُمْ إِلَى اللهِ."
    ],
    "hadith_application": [
      "يُمكِنُ تَطْبِيقُ الحَدِيثِ'سُئِلَ رَسُولُ اللهِ صَلَّى اللَّهُ عليه وَسَلَّمَ، عن أَطْفَالِ المُشْرِكِينَ؟ قالَ: اللَّهُ أَعْلَمُ بما كَانُوا عَامِلِينَ إذْ خَلَقَهُمْ.' فِي الحَيَاةِ اليَوْمِيَّةِ بِالتَّوَكُّلِ عَلَى حِكْمَةِ اللهِ فِي الأُمُورِ الغَيْبِيَّةِ الَّتِي لَا عِلْمَ لَنَا بِهَا، وَعَدَمِ الجَزَعِ أَوِ القَلَقِ عَلَى مَصِيرِ مَنْ لَا نَعْلَمُ حَالَهُمْ، مَعَ الدُّعَاءِ لَهُمْ بِالهُدَى وَالرَّحْمَةِ. كَمَا يَنْبَغِي التَّرَبِّي عَلَى تَقْوَى اللهِ وَحُسْنِ العِبَادَةِ لِأَنَّ المَصِيرَ بِيدِ اللهِ."
    ],
    "FT_Pairs": [
      {
        "question": "مَا هِيَ الرَّسَائِلُ الرَّئِيسِيَّةُ وَالدُّرُوسُ المُسْتَفَادَةُ والفَوَائِد المُستَخلصَة مِنَ الحَدِيثِ'سُئِلَ رَسُولُ اللهِ صَلَّى اللَّهُ عليه وَسَلَّمَ، عن أَطْفَالِ المُشْرِكِينَ؟ قالَ: اللَّهُ أَعْلَمُ بما كَانُوا عَامِلِينَ إذْ خَلَقَهُمْ.'؟",
        "answer": "يُستَفادُ مِنَ الحَدِيثِ أَنَّ أَمْرَ أَطْفَالِ المُشْرِكِينَ مَوْكُولٌ إِلَى عِلْمِ اللهِ تَعَالَى، وَأَنَّهُ سُبْحَانَهُ يَعْلَمُ مَا كَانُوا سَيَفْعَلُونَ لَوْ بَلَغُوا، وَيُجَازِيهِمْ بِحَسَبِ ذَلِكَ. وَفِيهِ تَذْكِيرٌ بِأَهَمِّيَّةِ التَّوَكُّلِ عَلَى حِكْمَةِ اللهِ وَعَدْلِهِ، وَأَنَّ العِلْمَ بِمَصِيرِهِمْ مَحْجُوبٌ عَنَّا، فَنَتَوَقَّفُ فِي الحُكْمِ عَلَيْهِمْ وَنُفَوِّضُ أَمْرَهُمْ إِلَى اللهِ."
      },
      {
        "question": "كَيْفَ يُمْكِنُ تَطْبِيقُ الحَدِيثِ'سُئِلَ رَسُولُ اللهِ صَلَّى اللَّهُ عليه وَسَلَّمَ، عن أَطْفَالِ المُشْرِكِينَ؟ قالَ: اللَّهُ أَعْلَمُ بما كَانُوا عَامِلِينَ إذْ خَلَقَهُمْ.' فِي الحَيَاةِ اليَوْمِيَّةِ؟",
        "answer": "يُمكِنُ تَطْبِيقُ الحَدِيثِ فِي الحَيَاةِ اليَوْمِيَّةِ بِالتَّوَكُّلِ عَلَى حِكْمَةِ اللهِ فِي الأُمُورِ الغَيْبِيَّةِ الَّتِي لَا عِلْمَ لَنَا بِهَا، وَعَدَمِ الجَزَعِ أَوِ القَلَقِ عَلَى مَصِيرِ مَنْ لَا نَعْلَمُ حَالَهُمْ، مَعَ الدُّعَاءِ لَهُمْ بِالهُدَى وَالرَّحْمَةِ. كَمَا يَنْبَغِي التَّرَبِّي عَلَى تَقْوَى اللهِ وَحُسْنِ العِبَادَةِ لِأَنَّ المَصِيرَ بِيدِ اللهِ."
      },
      {
        "question": "مَا أَهَمِّيَّةُ الحَدِيثِ'سُئِلَ رَسُولُ اللهِ صَلَّى اللَّهُ عليه وَسَلَّمَ، عن أَطْفَالِ المُشْرِكِينَ؟ قالَ: اللَّهُ أَعْلَمُ بما كَانُوا عَامِلِينَ إذْ خَلَقَهُمْ.' فِي الفِقْهِ الإِسْلَامِيِّ؟",
        "answer": "لِلحَدِيثِ أَهَمِّيَّةٌ كَبِيرَةٌ فِي الفِقْهِ الإِسْلَامِيِّ، حَيْثُ يُنَاقِشُ مَسْأَلَةً خِلَافِيَّةً بَيْنَ العُلَمَاءِ حَوْلَ مَصِيرِ أَطْفَالِ المُشْرِكِينَ. فَمِنْهُمْ مَنْ قَالَ بِأَنَّهُمْ فِي الجَنَّةِ لِعَدَمِ تَكْلِيفِهِمْ، وَمِنْهُمْ مَنْ تَوَقَّفَ فِي الحُكْمِ، وَمِنْهُمْ مَنْ ذَهَبَ إِلَى أَنَّهُمْ يُمْتَحَنُونَ يَوْمَ القِيَامَةِ. وَالحَدِيثُ يُؤَكِّدُ أَنَّ العِلْمَ بِمَصِيرِهِمْ عِنْدَ اللهِ."
      },
      {
        "question": "مَا سَبَبُ وُرُودِ الحَدِيثِ'سُئِلَ رَسُولُ اللهِ صَلَّى اللَّهُ عليه وَسَلَّمَ، عن أَطْفَالِ المُشْرِكِينَ؟ قالَ: اللَّهُ أَعْلَمُ بما كَانُوا عَامِلِينَ إذْ خَلَقَهُمْ.'؟",
        "answer": "سَبَبُ رِوَايَةِ الحَدِيثِ هُوَ سُؤَالُ الصَّحَابَةِ رَضِيَ اللهُ عَنْهُم عَنْ مَصِيرِ أَطْفَالِ المُشْرِكِينَ الَّذِينَ مَاتُوا قَبْلَ البُلُوغِ، فَأَجَابَهُمُ النَّبِيُّ صَلَّى اللهُ عَلَيْهِ وَسَلَّمَ بِأَنَّ اللهَ أَعْلَمُ بِمَا كَانُوا سَيَفْعَلُونَ لَوْ عَاشُوا، مُؤَكِّدًا عَلَى أَنَّ الأَمْرَ مَرْجِعُهُ إِلَى عِلْمِ اللهِ وَحِكْمَتِهِ."
      }
    ]
  }
]