{
    "hadith_id": "4166",
    "hadith": "سَمِعْتُ عَبْدَ اللَّهِ بنَ أبِي أوْفَى، وكانَ مِن أصْحَابِ الشَّجَرَةِ، قالَ: كانَ النبيُّ صَلَّى اللهُ عليه وسلَّمَ إذَا أتَاهُ قَوْمٌ بصَدَقَةٍ قالَ: اللَّهُمَّ صَلِّ عليهم. فأتَاهُ أبِي بصَدَقَتِهِ، فَقالَ: اللَّهُمَّ صَلِّ علَى آلِ أبِي أوْفَى.",
    "rawi": "عبدالله بن أبي أوفى",
    "mohdith": "البخاري",
    "book": "صحيح البخاري",
    "numberOrPage": "4166",
    "grade": "[صحيح]",
    "sharh": "لقدْ ضرَبَ لنا النبيُّ صلَّى اللهُ عليه وسلَّمَ أروعَ الأمثلةِ في حُسنِ الخُلقِ، ومِن حُسْنِ خُلقِه صلَّى اللهُ عليه وسلَّمَ مُكافأتُه لمَن أدَّى واجبًا، أو أسْدَى مَعروفًا.\nوفي هذا الحَديثِ يَحكي عَبدُ اللهِ بنُ أبي أَوْفَى رَضيَ اللهُ عنهما أنَّ النبيَّ صلَّى الله علَيه وسلَّمَ كانَ إذا أتاهُ قَومٌ بِصَدقتِهم -أي: بزَكاةِ أموالِهم- قالَ: «اللَّهُمَّ صَلِّ على آلِ فُلان»، أي: اغفِرْ لهُم وارْحَمْهم، فأتاهُ والدُه أبو أَوْفَى عَلقمةُ بنُ خالدِ بنِ الحارثِ الأسْلَميُّ بِصَدَقتِه، فقالَ النبيُّ صلَّى الله علَيه وسلَّمَ: «اللَّهُمَّ صَلِّ علَى آلِ أبي أَوْفَى»، وإضافةُ «الآلِ» لأبي أَوفَى للتَّشريفِ والتَّعظيمِ، ودُعاؤُه صلَّى اللهُ عليه وسلَّمَ لهم هو امتِثالٌ لِقولِه تعالَى: {خُذْ مِنْ أَمْوَالِهِمْ صَدَقَةً تُطَهِّرُهُمْ وَتُزَكِّيهِمْ بِهَا وَصَلِّ عَلَيْهِمْ إِنَّ صَلَاتَكَ سَكَنٌ لَهُمْ وَاللَّهُ سَمِيعٌ عَلِيمٌ} [التوبة: 103]، حيث أمَرَ اللهُ تعالَى نَبيَّه صلَّى اللهُ عليه وسلَّمَ بأخْذِ الصَّدَقةِ مِن الأموالِ، والدُّعاءِ للمُتصدِّقِ، فامتَثَلَ رَسولُ اللهِ صلَّى اللهُ عليه وسلَّمَ ذلك، فكان يَدْعو لمَن أتاهُ بصَدَقتِه.\nوفي الحديثِ: الصَّلاةُ على غَيرِ الأنْبياءِ.\nوفيه: الدُّعاءُ لِلمُتَصَدِّقِ.",
    "hadith_lessons": [],
    "hadith_application": [],
    "FT_Pairs": []
}