[
  {
    "hadith_id": 2467,
    "hadith": "أَشْرَفَ النبيُّ صَلَّى اللهُ عليه وسلَّمَ علَى أُطُمٍ مِن آطَامِ المَدِينَةِ، ثُمَّ قالَ: هلْ تَرَوْنَ ما أَرَى؟ إنِّي أَرَى مَوَاقِعَ الفِتَنِ خِلَالَ بُيُوتِكُمْ كَمَوَاقِعِ القَطْرِ.",
    "rawi": "أسامة بن زيد",
    "mohdith": "البخاري",
    "book": "صحيح البخاري",
    "hadith_number": 2467,
    "grade": "[صحيح]",
    "sharh": "كان النَّبيُّ صلَّى اللهُ عليه وسلَّمَ مُعلِّمًا ومُربِّيًا؛ يَستثمِرُ كُلَّ فُرصةٍ للدَّعوةِ إلى اللهِ تعالَى، وتَربيةِ أُمَّتِه على الخيرِ، وتَحذيرِهم مِن كلِّ شَرٍّ، ومِن ذلك الإخبارُ ببَعضِ ما سيَقَعُ في المستقبَلِ مِن فِتَنٍ وشُرورٍ كَي يَكونوا على حذَرٍ مِن أمْرِهم.\nوفي هذا الحَديثِ عَلَمٌ مِن أعلامِ نُبوَّتِه صلَّى اللهُ عليه وسلَّمَ، ومُعجزةٌ ظاهرةٌ له عليه الصَّلاةُ والسَّلامُ، حيثُ أخبَرَ ببَعضِ ما وقَعَ بعدَه؛ فيَرْوي أُسامةُ بنُ زَيدٍ أنَّ النَّبيَّ صلَّى اللهُ عليه وسلَّمَ ارْتَقَى أحدَ الحُصونِ أو الأبنيةِ المرتفعةِ بالمدينةِ ونظَرَ منه، ثمَّ لفَتَ انتباهَ مَن معه بقَولِه: «هل ترَوْنَ ما أرى؟»، ثمَّ أخبَرهم بما يَراه ببَصَرِه، وهو مَواضعُ سُقوطِ ونُزولِ الفِتَنِ الَّتي ستَكونُ في المدينةِ، كأنَّه يَراها في الفُرَجِ الَّتي بيْن البيوتِ، وأخبَرَهم أنَّها كَثيرةٌ وعامَّةٌ ككَثرةِ وعُمومِ مَواقعِ المطَرِ. والفتنُ هي الاختبارُ والابتلاءُ الَّذي يَحُلُّ في أُمورِ الدِّينِ أو الدُّنيا.\nوإنَّما اختُصَّتِ المدينةُ بذلك؛ لأنَّ قَتْلَ عُثمانَ رَضيَ اللهُ عنه كان بها، ثمَّ انتشَرَتِ الفِتَنُ في البلادِ بعدَ ذلك؛ فالقتالُ بالجَمَلِ وبصِفِّينَ كان بسَببِ قتْلِ عُثمانَ رَضيَ اللهُ عنه، والقِتالُ بالنَّهْروانِ كان بسَببِ التَّحكيمِ بصِفِّينَ، وكلُّ قِتالٍ وقَعَ في ذلك العصرِ إنَّما تولَّدَ عن شَيءٍ مِن ذلك، أو عن شَيءٍ تولَّد عنه.\nوفي الحديثِ: لَفْتُ الانتباهِ في التَّعليمِ مِن خِلالِ السُّؤالِ والجوابِ.",
    "hadith_lessons": "يُستَفَادُ مِنَ الحَدِيثِ'أَشْرَفَ النبيُّ صَلَّى اللهُ عليه وسلَّمَ علَى أُطُمٍ مِن آطَامِ المَدِينَةِ، ثُمَّ قالَ: هلْ تَرَوْنَ ما أَرَى؟ إنِّي أَرَى مَوَاقِعَ الفِتَنِ خِلَالَ بُيُوتِكُمْ كَمَوَاقِعِ القَطْرِ.' عِدَّةُ دُرُوسٍ وَفَوَائِدَ، مِنْهَا: تَحْذِيرُ النَّبِيِّ صَلَّى اللهُ عَلَيْهِ وَسَلَّمَ مِنَ الفِتَنِ وَشُرُورِهَا، وَإِخْبَارُهُ بِمَا سَيَقَعُ فِي المُسْتَقْبَلِ كَمُعْجِزَةٍ لِنُبُوَّتِهِ، وَتَرْبِيَةُ الأُمَّةِ عَلَى الحَذَرِ وَالِاسْتِعْدَادِ لِلتَّحَدِّيَاتِ الدِّينِيَّةِ وَالدُّنْيَوِيَّةِ، وَإِظْهَارُ عَظَمَةِ عِلْمِهِ صَلَّى اللهُ عَلَيْهِ وَسَلَّمَ بِالغَيْبِ.",
    "hadith_application": "يُمْكِنُ تَطْبِيقُ الحَدِيثِ'أَشْرَفَ النبيُّ صَلَّى اللهُ عليه وسلَّمَ علَى أُطُمٍ مِن آطَامِ المَدِينَةِ، ثُمَّ قالَ: هلْ تَرَوْنَ ما أَرَى؟ إنِّي أَرَى مَوَاقِعَ الفِتَنِ خِلَالَ بُيُوتِكُمْ كَمَوَاقِعِ القَطْرِ.' فِي الحَيَاةِ اليَوْمِيَّةِ بِالتَّحَذِيرِ مِنَ الفِتَنِ وَاجْتِنَابِهَا، وَالِاسْتِعْدَادِ لَهَا بِتَقْوَى اللهِ وَالِاعْتِصَامِ بِكِتَابِهِ وَسُنَّةِ نَبِيِّهِ، وَالتَّعَاوُنِ عَلَى البِرِّ وَالتَّقْوَى، وَتَجَنُّبِ كُلِّ مَا يُؤَدِّي إِلَى التَّفَرُّقِ وَالِاخْتِلَافِ.",
    "FT_Pairs": [
      {
        "question": "مَا هِيَ الرَّسَائِلُ الرَّئِيسِيَّةُ وَالدُّرُوسُ المُسْتَفَادَةُ والفَوَائِد المُستَخلصَة مِنَ الحَدِيثِ'أَشْرَفَ النبيُّ صَلَّى اللهُ عليه وسلَّمَ علَى أُطُمٍ مِن آطَامِ المَدِينَةِ، ثُمَّ قالَ: هلْ تَرَوْنَ ما أَرَى؟ إنِّي أَرَى مَوَاقِعَ الفِتَنِ خِلَالَ بُيُوتِكُمْ كَمَوَاقِعِ القَطْرِ.'؟",
        "answer": "يُستَفَادُ مِنَ الحَدِيثِ عِدَّةُ دُرُوسٍ وَفَوَائِدَ، مِنْهَا: تَحْذِيرُ النَّبِيِّ صَلَّى اللهُ عَلَيْهِ وَسَلَّمَ مِنَ الفِتَنِ وَشُرُورِهَا، وَإِخْبَارُهُ بِمَا سَيَقَعُ فِي المُسْتَقْبَلِ كَمُعْجِزَةٍ لِنُبُوَّتِهِ، وَتَرْبِيَةُ الأُمَّةِ عَلَى الحَذَرِ وَالِاسْتِعْدَادِ لِلتَّحَدِّيَاتِ الدِّينِيَّةِ وَالدُّنْيَوِيَّةِ، وَإِظْهَارُ عَظَمَةِ عِلْمِهِ صَلَّى اللهُ عَلَيْهِ وَسَلَّمَ بِالغَيْبِ."
      },
      {
        "question": "كَيْفَ يُمْكِنُ تَطْبِيقُ الحَدِيثِ'أَشْرَفَ النبيُّ صَلَّى اللهُ عليه وسلَّمَ علَى أُطُمٍ مِن آطَامِ المَدِينَةِ، ثُمَّ قالَ: هلْ تَرَوْنَ ما أَرَى؟ إنِّي أَرَى مَوَاقِعَ الفِتَنِ خِلَالَ بُيُوتِكُمْ كَمَوَاقِعِ القَطْرِ.' فِي الحَيَاةِ اليَوْمِيَّةِ؟",
        "answer": "يُمْكِنُ تَطْبِيقُ الحَدِيثِ فِي الحَيَاةِ اليَوْمِيَّةِ بِالتَّحَذِيرِ مِنَ الفِتَنِ وَاجْتِنَابِهَا، وَالِاسْتِعْدَادِ لَهَا بِتَقْوَى اللهِ وَالِاعْتِصَامِ بِكِتَابِهِ وَسُنَّةِ نَبِيِّهِ، وَالتَّعَاوُنِ عَلَى البِرِّ وَالتَّقْوَى، وَتَجَنُّبِ كُلِّ مَا يُؤَدِّي إِلَى التَّفَرُّقِ وَالِاخْتِلَافِ."
      },
      {
        "question": "مَا أَهَمِّيَّةُ الحَدِيثِ'أَشْرَفَ النبيُّ صَلَّى اللهُ عليه وسلَّمَ علَى أُطُمٍ مِن آطَامِ المَدِينَةِ، ثُمَّ قالَ: هلْ تَرَوْنَ ما أَرَى؟ إنِّي أَرَى مَوَاقِعَ الفِتَنِ خِلَالَ بُيُوتِكُمْ كَمَوَاقِعِ القَطْرِ.' فِي الفِقْهِ الإِسْلَامِيِّ؟",
        "answer": "لِلْحَدِيثِ أَهَمِّيَّةٌ كُبْرَى فِي الفِقْهِ الإِسْلَامِيِّ؛ حَيْثُ يُؤَكِّدُ عَلَى وَقَائِيَّةِ الشَّرِيعَةِ فِي التَّعَامُلِ مَعَ الفِتَنِ، وَيُبَيِّنُ أَهَمِّيَّةَ الحَذَرِ مِنْهَا وَاتِّبَاعِ السُّنَّةِ، كَمَا يُشِيرُ إِلَى أَهَمِّيَّةِ التَّرْبِيَةِ النَّبَوِيَّةِ وَالتَّعْلِيمِ بِأُسْلُوبِ السُّؤَالِ وَالجَوَابِ."
      },
      {
        "question": "مَا سَبَبُ وُرُودِ الحَدِيثِ'أَشْرَفَ النبيُّ صَلَّى اللهُ عليه وسلَّمَ علَى أُطُمٍ مِن آطَامِ المَدِينَةِ، ثُمَّ قالَ: هلْ تَرَوْنَ ما أَرَى؟ إنِّي أَرَى مَوَاقِعَ الفِتَنِ خِلَالَ بُيُوتِكُمْ كَمَوَاقِعِ القَطْرِ.'؟",
        "answer": "سَبَبُ رِوَايَةِ الحَدِيثِ هُوَ تَحْذِيرُ النَّبِيِّ صَلَّى اللهُ عَلَيْهِ وَسَلَّمَ أُمَّتَهُ مِنَ الفِتَنِ الَّتِي سَتَقَعُ بَعْدَهُ، خُصُوصًا فِي المَدِينَةِ المُنَوَّرَةِ، وَذَلِكَ لِيَكُونَ المُسْلِمُونَ عَلَى بَصِيرَةٍ وَحَذَرٍ، وَيُعَدُّ هَذَا مِنْ أَعْلَامِ نُبُوَّتِهِ وَمُعْجِزَاتِهِ، حَيْثُ أَخْبَرَ بِأُمُورٍ غَيْبِيَّةٍ وَقَعَتْ كَمَا تَنَبَّأَ بِهَا."
      }
    ]
  }
]