[
  {
    "hadith_id": "1469",
    "hadith": "إنَّ نَاسًا مِنَ الأنْصَارِ سَأَلُوا رَسولَ اللَّهِ صَلَّى اللهُ عليه وسلَّمَ فأعْطَاهُمْ، ثُمَّ سَأَلُوهُ فأعْطَاهُمْ، ثُمَّ سَأَلُوهُ فأعْطَاهُمْ، حتَّى نَفِدَ ما عِنْدَهُ، فَقَالَ: ما يَكونُ عِندِي مِن خَيْرٍ فَلَنْ أدَّخِرَهُ عَنْكُمْ، ومَن يَسْتَعْفِفْ يُعِفَّهُ اللَّهُ، ومَن يَسْتَغْنِ يُغْنِهِ اللَّهُ، ومَن يَتَصَبَّرْ يُصَبِّرْهُ اللَّهُ، وما أُعْطِيَ أحَدٌ عَطَاءً خَيْرًا وأَوْسَعَ مِنَ الصَّبْرِ.",
    "rawi": "أبو سعيد الخدري",
    "mohdith": "البخاري",
    "book": "صحيح البخاري",
    "numberOrPage": "1469",
    "grade": "[صحيح]",
    "sharh": "كان رَسولُ اللهِ صلَّى اللهُ عليه وسلَّمَ أجوَدَ بالخَيرِ مِن الرِّيحِ المُرسَلةِ، وكان يُعطِي عَطاءَ مَن لا يَخْشَى الفقْرَ، ومع سَعةِ إنفاقِه وُجودِه صلَّى اللهُ عليه وسلَّمَ كان يُربِّي النُّفوسَ على العَفافِ والاستغناءِ، وأنَّ ما عندَ اللهِ خَيرٌ وأبْقى.\nوفي هذا الحديثِ يَحكي أبو سَعيدٍ الخُدريُّ رَضيَ اللهُ عنه أنَّ ناسًا مِن الأنصارِ لم يُسَمِّهم سَأَلوا رَسولَ اللهِ صلَّى اللهُ عليه وسلَّمَ شَيئًا مِن المالِ فأعْطاهم، ثمَّ سَأَلوه فأعْطاهم، ثمَّ سَأَلوه فأَعْطاهم حتَّى نَفِدَ وانتَهى ما عِندَه مِن المالِ، فبيَّنَ لهم النبيُّ صلَّى اللهُ عليه وسلَّمَ أنَّه لا يَمنَعُ عنهم شيئًا مِن المالِ يكونُ عندَه فيَحتفَظ به لغَيرِهم.\nثمَّ أرشَدَهُم صلَّى اللهُ عليْه وسلَّمَ وحَثَّهم على الاستِعفافِ؛ فمَن تَخلَّقَ بالعِفَّةِ عمَّا حَرَّمَ اللهُ عليْه -سَواءٌ في مَأكَلٍ، أو مَشرَبٍ، أو مَلبَسٍ، ونَحوِ ذلك- أعانَه اللهُ عليْها وحَصَلَتْ له، ثمَّ حثَّهم صلَّى اللهُ عليْه وسلَّمَ على الاستِغناءِ، وهو أنْ يُسْتَغْنى الإنسانُ عمَّا في أيْدي النَّاسِ، ويَستَغنيَ بما عِندَه مِن اليَسيرِ عن المَسأَلةِ، فلا يَسألُ إلَّا إذا كان مُضطَرًّا، ومَن يَفعَلْ ذلك يَمُدَّه اللهُ عزَّ وجلَّ بالغِنى مِن عِندِه، ويَجعَلِ القَليلَ في عَينِه كَثيرًا، ثمَّ حثَّ صلَّى اللهُ عليْه وسلَّمَ على الْتِزامِ الصَّبرِ وتَعويدِ النَّفسِ عليْه؛ لأنَّ الإنسانَ إذا صَبَرَ استَعفَفَ واستَغْنى، ولم يَحصُلْ منه السُّؤالُ والإلْحافُ في المَسأَلةِ.\nوقولُه: «ومَن يَتَصبَّرْ يُصَبِّرْه اللهُ»، أي: ومَن يُعالِجِ نفْسَه بالصَّبرِ ويَتَكلَّفْه على ضِيقِ العَيشِ وغَيرِه مِن مَكارِه الدُّنيا؛ يَملَأِ اللهُ قَلْبَه به، ومَن بَذَلَ الأسبابَ وحَرَصَ على الصَّبرِ؛ فإنَّ اللهَ تعالَى يُوفِّقُه لتَحصيلِه، ويَجعَلُه يَتَّصفُ به.\nثمَّ بيَّن أنَّه ما أعْطَى اللهُ أحدًا نِعمةً ولا خُلُقًا كَريمًا أفضَلَ ولا أوسَعَ مِن الصَّبرِ؛ لأنَّه يَتَّسِعُ لكُلِّ الفَضائلِ، فكُلُّها تَصدُرُ عنه، وتَعتَمِدُ عليْه؛ مِن عِفَّةٍ، وشَجاعةٍ، وعَزيمةٍ، وإرادةٍ، وإباءٍ، وغَيرِها، والإنسانُ إذا كان صَبورًا تَحمَّلَ كُلَّ مَكروهٍ بإذْنِ اللهِ تعالَى.\nوفي الحَديثِ: أنَّ الأخلاقَ الكريمةَ يُمكِنُ اكتِسابُها والوصولُ إليها عن طَريقِ التعوُّدِ عليها.\nوفيه: ما كان عليه النبيُّ صلَّى اللهُ عليه وسلَّمَ مِن الكَرَمِ والسَّخاءِ والإيثارِ على نفْسِه.\nوفيه: الاعتِذارُ للسَّائلِ إذا لم يَجِدِ المسؤولُ ما يُعطِيه.\nوفيه: الحَضُّ على الاستِغناءِ عن النَّاسِ بالصَّبرِ، والتَّوكُّلِ على اللهِ، وانتظارِ رِزقِ اللهِ سُبحانَه، وأنَّ الصَّبرَ أفضلُ ما أُعطيَه المؤمنُ، وكذلك الجَزاءُ عليه غيرُ مُقدَّرٍ ولا مَحدودٍ.",
    "hadith_lessons": [
      "يُستَفَادُ مِنَ الحَدِيثِ'إنَّ نَاسًا مِنَ الأنْصَارِ سَأَلُوا رَسولَ اللَّهِ صَلَّى اللهُ عليه وسلَّمَ فأعْطَاهُمْ، ثُمَّ سَأَلُوهُ فأعْطَاهُمْ، ثُمَّ سَأَلُوهُ فأعْطَاهُمْ، حتَّى نَفِدَ ما عِنْدَهُ، فَقَالَ: ما يَكونُ عِندِي مِن خَيْرٍ فَلَنْ أدَّخِرَهُ عَنْكُمْ، ومَن يَسْتَعْفِفْ يُعِفَّهُ اللَّهُ، ومَن يَسْتَغْنِ يُغْنِهِ اللَّهُ، ومَن يَتَصَبَّرْ يُصَبِّرْهُ اللَّهُ، وما أُعْطِيَ أحَدٌ عَطَاءً خَيْرًا وأَوْسَعَ مِنَ الصَّبْرِ.' عِدَّةُ دُرُوسٍ وَفَوَائِدَ، مِنْهَا: تَرْبِيَةُ النُّفُوسِ عَلَى العَفَافِ وَالِاسْتِغْنَاءِ عَنْ مَسْأَلَةِ النَّاسِ، وَأَنَّ مَا عِنْدَ اللَّهِ خَيْرٌ وَأَبْقَى، وَأَنَّ الصَّبْرَ أَفْضَلُ مَا يُعْطَى الْمُؤْمِنُ، وَأَنَّ الْأَخْلَاقَ الْكَرِيمَةَ يُمْكِنُ اكْتِسَابُهَا بِالتَّعَوُّدِ وَالْمُجَاهَدَةِ، وَأَنَّ الْكَرَمَ وَالسَّخَاءَ مِنْ صِفَاتِ النَّبِيِّ صَلَّى اللَّهُ عَلَيْهِ وَسَلَّمَ."
    ],
    "hadith_application": [
      "يُمْكِنُ تَطْبِيقُ الحَدِيثِ'إنَّ نَاسًا مِنَ الأنْصَارِ سَأَلُوا رَسولَ اللَّهِ صَلَّى اللهُ عليه وسلَّمَ فأعْطَاهُمْ، ثُمَّ سَأَلُوهُ فأعْطَاهُمْ، ثُمَّ سَأَلُوهُ فأعْطَاهُمْ، حتَّى نَفِدَ ما عِنْدَهُ، فَقَالَ: ما يَكونُ عِندِي مِن خَيْرٍ فَلَنْ أدَّخِرَهُ عَنْكُمْ، ومَن يَسْتَعْفِفْ يُعِفَّهُ اللَّهُ، ومَن يَسْتَغْنِ يُغْنِهِ اللَّهُ، ومَن يَتَصَبَّرْ يُصَبِّرْهُ اللَّهُ، وما أُعْطِيَ أحَدٌ عَطَاءً خَيْرًا وأَوْسَعَ مِنَ الصَّبْرِ.' فِي الحَيَاةِ اليَوْمِيَّةِ بِالتَّخَلُّقِ بِالعَفَافِ وَالِاسْتِغْنَاءِ عَنْ مَسْأَلَةِ النَّاسِ، وَالصَّبْرِ عَلَى ضِيقِ الحَالِ، وَالتَّوَكُّلِ عَلَى اللَّهِ تَعَالَى، وَالاِعْتِمَادِ عَلَى مَا عِنْدَ اللَّهِ، وَالاِحْتِفَاظِ بِالْأَخْلَاقِ الْكَرِيمَةِ مِثْلَ الصَّبْرِ وَالشَّجَاعَةِ وَالعَزِيمَةِ."
    ],
    "FT_Pairs": [
      {
        "question": "مَا هِيَ الرَّسَائِلُ الرَّئِيسِيَّةُ وَالدُّرُوسُ المُسْتَفَادَةُ والفَوَائِد المُستَخلصَة مِنَ الحَدِيثِ'إنَّ نَاسًا مِنَ الأنْصَارِ سَأَلُوا رَسولَ اللَّهِ صَلَّى اللهُ عليه وسلَّمَ فأعْطَاهُمْ، ثُمَّ سَأَلُوهُ فأعْطَاهُمْ، ثُمَّ سَأَلُوهُ فأعْطَاهُمْ، حتَّى نَفِدَ ما عِنْدَهُ، فَقَالَ: ما يَكونُ عِندِي مِن خَيْرٍ فَلَنْ أدَّخِرَهُ عَنْكُمْ، ومَن يَسْتَعْفِفْ يُعِفَّهُ اللَّهُ، ومَن يَسْتَغْنِ يُغْنِهِ اللَّهُ، ومَن يَتَصَبَّرْ يُصَبِّرْهُ اللَّهُ، وما أُعْطِيَ أحَدٌ عَطَاءً خَيْرًا وأَوْسَعَ مِنَ الصَّبْرِ.'؟",
        "answer": "يُستَفَادُ مِنَ الحَدِيثِ عِدَّةُ دُرُوسٍ وَفَوَائِدَ، مِنْهَا: تَرْبِيَةُ النُّفُوسِ عَلَى العَفَافِ وَالِاسْتِغْنَاءِ عَنْ مَسْأَلَةِ النَّاسِ، وَأَنَّ مَا عِنْدَ اللَّهِ خَيْرٌ وَأَبْقَى، وَأَنَّ الصَّبْرَ أَفْضَلُ مَا يُعْطَى الْمُؤْمِنُ، وَأَنَّ الْأَخْلَاقَ الْكَرِيمَةَ يُمْكِنُ اكْتِسَابُهَا بِالتَّعَوُّدِ وَالْمُجَاهَدَةِ، وَأَنَّ الْكَرَمَ وَالسَّخَاءَ مِنْ صِفَاتِ النَّبِيِّ صَلَّى اللَّهُ عَلَيْهِ وَسَلَّمَ."
      },
      {
        "question": "كَيْفَ يُمْكِنُ تَطْبِيقُ الحَدِيثِ'إنَّ نَاسًا مِنَ الأنْصَارِ سَأَلُوا رَسولَ اللَّهِ صَلَّى اللهُ عليه وسلَّمَ فأعْطَاهُمْ، ثُمَّ سَأَلُوهُ فأعْطَاهُمْ، ثُمَّ سَأَلُوهُ فأعْطَاهُمْ، حتَّى نَفِدَ ما عِنْدَهُ، فَقَالَ: ما يَكونُ عِندِي مِن خَيْرٍ فَلَنْ أدَّخِرَهُ عَنْكُمْ، ومَن يَسْتَعْفِفْ يُعِفَّهُ اللَّهُ، ومَن يَسْتَغْنِ يُغْنِهِ اللَّهُ، ومَن يَتَصَبَّرْ يُصَبِّرْهُ اللَّهُ، وما أُعْطِيَ أحَدٌ عَطَاءً خَيْرًا وأَوْسَعَ مِنَ الصَّبْرِ.' فِي الحَيَاةِ اليَوْمِيَّةِ؟",
        "answer": "يُمْكِنُ تَطْبِيقُ الحَدِيثِ فِي الحَيَاةِ اليَوْمِيَّةِ بِالتَّخَلُّقِ بِالعَفَافِ وَالِاسْتِغْنَاءِ عَنْ مَسْأَلَةِ النَّاسِ، وَالصَّبْرِ عَلَى ضِيقِ الحَالِ، وَالتَّوَكُّلِ عَلَى اللَّهِ تَعَالَى، وَالاِعْتِمَادِ عَلَى مَا عِنْدَ اللَّهِ، وَالاِحْتِفَاظِ بِالْأَخْلَاقِ الْكَرِيمَةِ مِثْلَ الصَّبْرِ وَالشَّجَاعَةِ وَالعَزِيمَةِ."
      },
      {
        "question": "مَا أَهَمِّيَّةُ الحَدِيثِ'إنَّ نَاسًا مِنَ الأنْصَارِ سَأَلُوا رَسولَ اللَّهِ صَلَّى اللهُ عليه وسلَّمَ فأعْطَاهُمْ، ثُمَّ سَأَلُوهُ فأعْطَاهُمْ، ثُمَّ سَأَلُوهُ فأعْطَاهُمْ، حتَّى نَفِدَ ما عِنْدَهُ، فَقَالَ: ما يَكونُ عِندِي مِن خَيْرٍ فَلَنْ أدَّخِرَهُ عَنْكُمْ، ومَن يَسْتَعْفِفْ يُعِفَّهُ اللَّهُ، ومَن يَسْتَغْنِ يُغْنِهِ اللَّهُ، ومَن يَتَصَبَّرْ يُصَبِّرْهُ اللَّهُ، وما أُعْطِيَ أحَدٌ عَطَاءً خَيْرًا وأَوْسَعَ مِنَ الصَّبْرِ.' فِي الفِقْهِ الإِسْلَامِيِّ؟",
        "answer": "لِلْحَدِيثِ أَهَمِّيَّةٌ كَبِيرَةٌ فِي الفِقْهِ الإِسْلَامِيِّ، حَيْثُ يُؤَكِّدُ عَلَى أَهَمِّيَّةِ الصَّبْرِ وَالعَفَافِ وَالِاسْتِغْنَاءِ، وَيُبَيِّنُ أَنَّ الصَّبْرَ أَفْضَلُ مَا يُعْطَى الْمُؤْمِنُ، وَيُشِيرُ إِلَى أَنَّ الْأَخْلَاقَ الْكَرِيمَةَ قَابِلَةٌ لِلِاكْتِسَابِ، وَيُؤَصِّلُ لِمَبْدَأِ الكَرَمِ وَالسَّخَاءِ فِي الإِسْلَامِ."
      },
      {
        "question": "مَا سَبَبُ وُرُودِ الحَدِيثِ'إنَّ نَاسًا مِنَ الأنْصَارِ سَأَلُوا رَسولَ اللَّهِ صَلَّى اللهُ عليه وسلَّمَ فأعْطَاهُمْ، ثُمَّ سَأَلُوهُ فأعْطَاهُمْ، ثُمَّ سَأَلُوهُ فأعْطَاهُمْ، حتَّى نَفِدَ ما عِنْدَهُ، فَقَالَ: ما يَكونُ عِندِي مِن خَيْرٍ فَلَنْ أدَّخِرَهُ عَنْكُمْ، ومَن يَسْتَعْفِفْ يُعِفَّهُ اللَّهُ، ومَن يَسْتَغْنِ يُغْنِهِ اللَّهُ، ومَن يَتَصَبَّرْ يُصَبِّرْهُ اللَّهُ، وما أُعْطِيَ أحَدٌ عَطَاءً خَيْرًا وأَوْسَعَ مِنَ الصَّبْرِ.'؟",
        "answer": "سَبَبُ رِوَايَةِ الحَدِيثِ هُوَ حَدَثٌ وَقَعَ حِينَ سَأَلَ نَاسٌ مِنَ الأَنْصَارِ النَّبِيَّ صَلَّى اللَّهُ عَلَيْهِ وَسَلَّمَ المَالَ فَأَعْطَاهُمْ حَتَّى نَفِدَ مَا عِنْدَهُ، فَبَيَّنَ لَهُمْ أَنَّهُ لَا يَمْنَعُهُمْ شَيْئًا، وَأَرْشَدَهُمْ إِلَى العَفَافِ وَالِاسْتِغْنَاءِ وَالصَّبْرِ، لِيُرَبِّيَ فِيهِمُ التَّقْوَى وَالاِعْتِمَادَ عَلَى اللَّهِ تَعَالَى."
      }
    ]
  }
]