[
  {
    "hadith_id": "6503",
    "hadith": "بُعِثْتُ أنا والسَّاعَةَ هَكَذا ويُشِيرُ بإصْبَعَيْهِ فَيَمُدُّ بهِما.",
    "rawi": "سهل بن سعد الساعدي",
    "mohdith": "البخاري",
    "book": "صحيح البخاري",
    "numberOrPage": "6503",
    "grade": "[صحيح]",
    "takhrij": "أخرجه مسلم (2950)، وابن حبان (6642)، والطبراني في ((المعجم الكبير)) (6/ 188) (5953)، والروياني في ((مسنده)) (1017) جميعا بنحوه.",
    "sharh": "يومُ القيامةِ حَقٌّ آتٍ لا رَيبَ فيه، وقد مضى قَدَرُ اللهِ عزَّ وجَلَّ أن يأتيَ هذا اليومَ على النَّاسِ بَغتةً، ومِن رحمتِه سُبحانَه بالعِبادِ أن أقام لهم علاماتٍ تدُلُّهم على قُربِ وُقوعِها.\nوفي هذا الحَديثِ يَحكِي سَهْلُ بنُ سَعْدٍ رضِيَ اللهُ عنه أنَّه رَأى رَسولَ اللهِ صلَّى اللهُ عليه وسلَّم «قالَ بإصْبَعَيْهِ هَكَذَا»، أي: أشار، فالقَولُ هنا بمعنى الفِعلِ، «بالوُسْطَى والتي تَلِي الإبْهَامَ» وهي المُسَبِّحَةُ، وتُسَمَّى السَّبابةَ، قال: «بُعِثْتُ والسَّاعَةُ كهاتَيْنِ»، يعني: أنَّ السَّاعةَ وبَعثةَ النَّبيِّ صلَّى اللهُ عليه وسلَّم مُقتَرِنَانِ كاقتِرانِ الإصبَعَينِ، أو الفارِقُ بين بَعْثَتِه صلَّى اللهُ عليه وسلَّم وقيامِ السَّاعةِ كالفَرقِ بين الإصبَعَينِ في الطُّولِ، والمرادُ بيانُ قُربِ وقتِ قِيامِ السَّاعةِ.\nوفي الحَديثِ: أنَّ مِن أَشْرَاطِ السَّاعةِ وعَلاماتِها السَّابقةِ المتقدِّمةِ: بَعْثَةَ النَّبيِّ صلَّى اللهُ عليه وسلَّم؛ فإنَّ بَعْثَتَه صلَّى اللهُ عليه وسلَّم وكَونَه خَاتَمَ النَّبيِّين دَليلٌ على قُربِ السَّاعةِ.\nوفيه: أنَّ النَّبيَّ صلَّى اللهُ عليه وسلَّم خاتَمُ الأنبياءِ، وأمَّتُه صلَّى اللهُ عليه وسلَّم خاتِمةُ الأُمَمِ، وعليها تقومُ السَّاعةُ.",
    "hadith_lessons": [
      "الدُّرُوسُ وَالرَّسَائِلُ الرَّئِيسِيَّةُ مِنَ الحَدِيثِ'بُعِثْتُ أنا والسَّاعَةَ هَكَذا ويُشِيرُ بإصْبَعَيْهِ فَيَمُدُّ بهِما.': تَأكِيدُ حَقِيقَةِ قُرْبِ يَومِ القِيَامَةِ، وَأَنَّ بَعْثَةَ النَّبِيِّ صَلَّى اللهُ عَلَيهِ وَسَلَّمَ مِنْ أَشْرَاطِ السَّاعَةِ، وَأَنَّهُ خَاتَمُ الأَنْبِيَاءِ وَأُمَّتُهُ خَاتِمَةُ الأُمَمِ."
    ],
    "hadith_application": [
      "يُمكِنُ تَطْبِيقُ الحَدِيثِ'بُعِثْتُ أنا والسَّاعَةَ هَكَذا ويُشِيرُ بإصْبَعَيْهِ فَيَمُدُّ بهِما.' فِي الحَيَاةِ اليَوْمِيَّةِ بِالتَّذَكُّرِ الدَّائِمِ لِقُرْبِ يَومِ القِيَامَةِ، وَالاِسْتِعْدَادِ لَهُ بِالعَمَلِ الصَّالِحِ وَتَجَنُّبِ المَعَاصِي، وَالتَّأَسِّي بِالنَّبِيِّ صَلَّى اللهُ عَلَيهِ وَسَلَّمَ كَخَاتَمِ الأَنْبِيَاءِ."
    ],
    "FT_Pairs": [
      {
        "question": "مَا هِيَ الرَّسَائِلُ الرَّئِيسِيَّةُ وَالدُّرُوسُ المُسْتَفَادَةُ والفَوَائِد المُستَخلصَة مِنَ الحَدِيثِ'بُعِثْتُ أنا والسَّاعَةَ هَكَذا ويُشِيرُ بإصْبَعَيْهِ فَيَمُدُّ بهِما.'؟",
        "answer": "الدُّرُوسُ وَالرَّسَائِلُ الرَّئِيسِيَّةُ مِنَ الحَدِيثِ: تَأكِيدُ حَقِيقَةِ قُرْبِ يَومِ القِيَامَةِ، وَأَنَّ بَعْثَةَ النَّبِيِّ صَلَّى اللهُ عَلَيهِ وَسَلَّمَ مِنْ أَشْرَاطِ السَّاعَةِ، وَأَنَّهُ خَاتَمُ الأَنْبِيَاءِ وَأُمَّتُهُ خَاتِمَةُ الأُمَمِ."
      },
      {
        "question": "كَيْفَ يُمْكِنُ تَطْبِيقُ الحَدِيثِ'بُعِثْتُ أنا والسَّاعَةَ هَكَذا ويُشِيرُ بإصْبَعَيْهِ فَيَمُدُّ بهِما.' فِي الحَيَاةِ اليَوْمِيَّةِ؟",
        "answer": "يُمكِنُ تَطْبِيقُ الحَدِيثِ فِي الحَيَاةِ اليَوْمِيَّةِ بِالتَّذَكُّرِ الدَّائِمِ لِقُرْبِ يَومِ القِيَامَةِ، وَالاِسْتِعْدَادِ لَهُ بِالعَمَلِ الصَّالِحِ وَتَجَنُّبِ المَعَاصِي، وَالتَّأَسِّي بِالنَّبِيِّ صَلَّى اللهُ عَلَيهِ وَسَلَّمَ كَخَاتَمِ الأَنْبِيَاءِ."
      },
      {
        "question": "مَا أَهَمِّيَّةُ الحَدِيثِ'بُعِثْتُ أنا والسَّاعَةَ هَكَذا ويُشِيرُ بإصْبَعَيْهِ فَيَمُدُّ بهِما.' فِي الفِقْهِ الإِسْلَامِيِّ؟",
        "answer": "لِلحَدِيثِ أَهَمِّيَّةٌ كُبْرَى فِي الفِقْهِ الإِسْلَامِيِّ؛ حَيْثُ يُؤَكِّدُ عَقِيدَةَ القِيَامَةِ وَيُبَيِّنُ أَنَّ بَعْثَةَ النَّبِيِّ صَلَّى اللهُ عَلَيهِ وَسَلَّمَ مِنْ أَشْرَاطِهَا، وَيُثْبِتُ خَاتَمِيَّتَهُ لِلنُّبُوَّةِ وَخَاتَمِيَّةَ أُمَّتِهِ."
      },
      {
        "question": "مَا سَبَبُ وُرُودِ الحَدِيثِ'بُعِثْتُ أنا والسَّاعَةَ هَكَذا ويُشِيرُ بإصْبَعَيْهِ فَيَمُدُّ بهِما.'؟",
        "answer": "سَبَبُ رِوَايَةِ الحَدِيثِ هُوَ بَيَانُ قُرْبِ يَومِ القِيَامَةِ وَأَنَّ بَعْثَةَ النَّبِيِّ صَلَّى اللهُ عَلَيهِ وَسَلَّمَ مِنْ أَشْرَاطِهَا، لِتُحَفِّزَ النَّاسَ عَلَى الاِسْتِعْدَادِ لِهَذَا اليَومِ بِالعَمَلِ الصَّالِحِ."
      }
    ]
  }
]