{
    "hadith_id": "522",
    "hadith": "فُضِّلْنا علَى النَّاسِ بثَلاثٍ: جُعِلَتْ صُفُوفُنا كَصُفُوفِ المَلائِكَةِ، وجُعِلَتْ لنا الأرْضُ كُلُّها مَسْجِدًا، وجُعِلَتْ تُرْبَتُها لنا طَهُورًا، إذا لَمْ نَجِدِ الماءَ وذَكَرَ خَصْلَةً أُخْرَى.",
    "rawi": "حذيفة بن اليمان",
    "mohdith": "مسلم",
    "book": "صحيح مسلم",
    "numberOrPage": "522",
    "grade": "[صحيح]",
    "takhrij": "من أفراد مسلم على البخاري",
    "sharh": "في هذا الحديثِ يَقولُ النَّبيُّ صلَّى اللهُ عليه وسلَّم مُتحدِّثًا بنِعمَةِ اللهِ ومُبيِّنًا لأحكامِ شَرعِه: \"فُضِّلْنَا على النَّاسِ\"، أي: فَضَّلنَا اللهُ على جميعِ الأُممِ السَّالفةِ بثَلاثِ خِصالٍ لم تَكُنْ لهم وَاحدةٌ منها، ومَفهومُ العَددِ غَيرُ مُرادٍ، لأنَّه قد ثَبَتَ أنَّه فُضِّلَ بأكثرَ من ذلك. \r\nالخِصلَةُ الأولى هي قَولُه صلَّى اللهُ عليه وسلَّم: \"جُعِلَتْ صُفوفُنا\"، أي: وُقوفُنا في الصَّلاةِ، \"كصفوفِ الملائِكَةِ\". قيل: في المعركَةِ، وقيل: في الصَّلاةِ، وقيل: في الطَّاعةِ، وهي أنَّهم يُتِمُّونَ المُقدَّمَ، ثُمَّ الَّذي يليه من الصُّفوفِ، ثُمَّ يُراصُّونَ الصُّفوفَ.\r\nوالخصلَةُ الثَّانيةُ هي قَولُه صلَّى اللهُ عليه وسلَّم:\"وجُعِلتْ لنا الأرضُ كُلُّها مسجدًا\"، أي: موضعًا للسُّجودِ، أي: لا يَختَصُّ السُّجودُ منها بموضعٍ دون موضعٍ، وهذا من فَضْلِ اللهِ على هذه الأُمَّة أنَّها لم تُقصَرْ مساجِدُها على بِقاعٍ محصورَةٍ، \"وجُعِلت تُربَتُها لنا طَهورًا\"، أي: تُرابُ الأرضِ، \"لنا طَهورًا\"، أي: مُطهِّرًا إذا لم نجدِ الماءَ. \r\nوذَكر خَصلَةً أُخرَى، ظاهِرُه أنَّه ذَكَرَ ثلاثَ خِصالٍ، وإنَّما هما اثنتانِ كما ذُكِر؛ لأنَّ قَضيَّةَ الأرضِ كُلَّها خَصلةٌ واحدةٌ، والخَصلَةُ الثَّالثةُ غَيرُ مَذكورةٍ في هذا الحديثِ، وهذه الخَصلَةُ المُبْهَمةُ بيَّنَها ابنُ خُزَيْمَةَ والنَّسَائِيُّ، وهي: \" وأُعطيتُ هذه الآياتِ من آخِرِ سورةِ البَقَرةِ من كَنزٍ تحتَ العرشِ\"، يُشيرُ إلى ما حَطَّه اللهُ عن أُمَّته من الإِصْرِ وتحميلِ ما لا طَاقَةَ لهم به، ورَفعِ الخطأِ والنسيانِ .",
    "hadith_lessons": [],
    "hadith_application": [],
    "FT_Pairs": []
}