[
  {
    "hadith_id": "1184",
    "hadith": "سَمِعْتُ مَرْثَدَ بنَ عبدِ اللَّهِ اليَزَنِيَّ، قالَ: أتَيْتُ عُقْبَةَ بنَ عَامِرٍ الجُهَنِيَّ، فَقُلتُ: ألَا أُعْجِبُكَ مِن أبِي تَمِيمٍ؟ يَرْكَعُ رَكْعتَيْنِ قَبْلَ صَلَاةِ المَغْرِبِ! فَقالَ عُقْبَةُ: إنَّا كُنَّا نَفْعَلُهُ علَى عَهْدِ رَسولِ اللَّهِ صلَّى اللهُ عليه وسلَّمَ، قُلتُ: فَما يَمْنَعُكَ الآنَ؟ قالَ: الشُّغْلُ.",
    "rawi": "عقبة بن عامر",
    "mohdith": "البخاري",
    "book": "صحيح البخاري",
    "numberOrPage": "1184",
    "grade": "[صحيح]",
    "takhrij": "أخرجه أحمد (17416)، والطبراني في ((المعجم الأوسط)) (9336)، والبيهقي (4554) جميعهم بلفظه.",
    "sharh": "شُرِعَت صَلواتِ النَّوافلُ قبْلَ صَلواتِ الفَرائضِ وبعْدَها لتَهيئةِ النُّفوسِ للصَّلاةِ، ولتَكونَ جَبْرًا لِما عَسى أنْ يَقَعَ فيها مِن نَقْصٍ.\r\nوفي هذا الحديثِ يُخبِرُ التابعيُّ مَرْثَدُ بنُ عبدِ اللهِ اليَزَنيُّ أنَّه أتَى إلى الصَّحابيِّ عُقْبةَ بنِ عَامِرٍ الجُهَنِيِّ رَضيَ اللهُ عنه، فقال له: ألَا أُخبِرُك أمْرًا تَتعجَّبُ فيه مِن أبي تَميمٍ؟! وهو عبدُ اللهِ بنُ مالكٍ، كان مِن التَّابعينَ، فأخْبَرَه أنَّه يُصلِّي رَكعتَينِ نافلةً قبْلَ صَلاةِ المغربِ فيما بيْنَ الأذانِ والإقامةِ، فردَّ عليه عُقبةُ بنُ عامرٍ رَضيَ اللهُ عنه بأنَّهم كانوا يُصَلُّون هاتَينِ الرَّكعتَينِ قبْلَ المغربِ على عهْدِ النبيِّ صلَّى اللهُ عليه وسلَّمَ، ولكنْ مَنَعَ عُقبةَ بنَ عامرٍ رَضيَ اللهُ عنه عن صَلاتِها الآنَ الانشغالُ.\r\nوالرَّكعتانِ قبْلَ المغربِ حثَّ عليهما النبيُّ صلَّى اللهُ عليه وسلَّمَ، كما في صَحيحِ البُخاريِّ عن عَبدِ اللهِ بنِ مُغفَّلٍ المُزَنيِّ رَضيَ اللهُ عنه، قال صلَّى اللهُ عليه وسلَّمَ: «صَلُّوا قبْلَ صَلاةِ المَغْرِب، قالَ في الثَّالِثةِ: لِمَن شَاءَ؛ كَراهيةَ أنْ يَتَّخِذَها النَّاسُ سُنَّةً». \r\nوفي الحديثِ: مَشروعيَّةُ التَّنفُّلِ قبْلَ المغربِ.",
    "hadith_lessons": [
      "يُستَفَادُ مِنَ الحَدِيثِ'سَمِعْتُ مَرْثَدَ بنَ عبدِ اللَّهِ اليَزَنِيَّ، قالَ: أتَيْتُ عُقْبَةَ بنَ عَامِرٍ الجُهَنِيَّ، فَقُلتُ: ألَا أُعْجِبُكَ مِن أبِي تَمِيمٍ؟ يَرْكَعُ رَكْعتَيْنِ قَبْلَ صَلَاةِ المَغْرِبِ! فَقالَ عُقْبَةُ: إنَّا كُنَّا نَفْعَلُهُ علَى عَهْدِ رَسولِ اللَّهِ صلَّى اللهُ عليه وسلَّمَ، قُلتُ: فَما يَمْنَعُكَ الآنَ؟ قالَ: الشُّغْلُ.' مَشْرُوعِيَّةُ صَلَاةِ الرَّكْعَتَيْنِ قَبْلَ صَلَاةِ المَغْرِبِ، وَأَنَّهَا كَانَتْ مَفْعُولَةً فِي عَهْدِ النَّبِيِّ صَلَّى اللهُ عَلَيْهِ وَسَلَّمَ، وَأَنَّهَا تَكُونُ جَبْرًا لِنَقْصِ الفَرِيضَةِ، وَتَهْيِئَةً لِلنَّفْسِ لِلدُّخُولِ فِي الصَّلَاةِ."
    ],
    "hadith_application": [
      "يُمكِنُ تَطْبِيقُ الحَدِيثِ'سَمِعْتُ مَرْثَدَ بنَ عبدِ اللَّهِ اليَزَنِيَّ، قالَ: أتَيْتُ عُقْبَةَ بنَ عَامِرٍ الجُهَنِيَّ، فَقُلتُ: ألَا أُعْجِبُكَ مِن أبِي تَمِيمٍ؟ يَرْكَعُ رَكْعتَيْنِ قَبْلَ صَلَاةِ المَغْرِبِ! فَقالَ عُقْبَةُ: إنَّا كُنَّا نَفْعَلُهُ علَى عَهْدِ رَسولِ اللَّهِ صلَّى اللهُ عليه وسلَّمَ، قُلتُ: فَما يَمْنَعُكَ الآنَ؟ قالَ: الشُّغْلُ.' فِي الحَيَاةِ اليَوْمِيَّةِ بِالإِقْبَالِ عَلَى صَلَاةِ الرَّكْعَتَيْنِ قَبْلَ المَغْرِبِ، وَالاجْتِهَادِ فِي أَدَاءِ النَّوَافِلِ لِتَكْمِيلِ الفَرَائِضِ وَالتَّقَرُّبِ إِلَى اللهِ تَعَالَى، مَعَ مُرَاعَاةِ عَدَمِ التَّشْدِيدِ عَلَى النَّفْسِ فِي حَالِ الانْشِغَالِ."
    ],
    "FT_Pairs": [
      {
        "question": "مَا هِيَ الرَّسَائِلُ الرَّئِيسِيَّةُ وَالدُّرُوسُ المُسْتَفَادَةُ والفَوَائِد المُستَخلصَة مِنَ الحَدِيثِ'سَمِعْتُ مَرْثَدَ بنَ عبدِ اللَّهِ اليَزَنِيَّ، قالَ: أتَيْتُ عُقْبَةَ بنَ عَامِرٍ الجُهَنِيَّ، فَقُلتُ: ألَا أُعْجِبُكَ مِن أبِي تَمِيمٍ؟ يَرْكَعُ رَكْعتَيْنِ قَبْلَ صَلَاةِ المَغْرِبِ! فَقالَ عُقْبَةُ: إنَّا كُنَّا نَفْعَلُهُ علَى عَهْدِ رَسولِ اللَّهِ صلَّى اللهُ عليه وسلَّمَ، قُلتُ: فَما يَمْنَعُكَ الآنَ؟ قالَ: الشُّغْلُ.'؟",
        "answer": "يُستَفَادُ مِنَ الحَدِيثِ مَشْرُوعِيَّةُ صَلَاةِ الرَّكْعَتَيْنِ قَبْلَ صَلَاةِ المَغْرِبِ، وَأَنَّهَا كَانَتْ مَفْعُولَةً فِي عَهْدِ النَّبِيِّ صَلَّى اللهُ عَلَيْهِ وَسَلَّمَ، وَأَنَّهَا تَكُونُ جَبْرًا لِنَقْصِ الفَرِيضَةِ، وَتَهْيِئَةً لِلنَّفْسِ لِلدُّخُولِ فِي الصَّلَاةِ."
      },
      {
        "question": "كَيْفَ يُمْكِنُ تَطْبِيقُ الحَدِيثِ'سَمِعْتُ مَرْثَدَ بنَ عبدِ اللَّهِ اليَزَنِيَّ، قالَ: أتَيْتُ عُقْبَةَ بنَ عَامِرٍ الجُهَنِيَّ، فَقُلتُ: ألَا أُعْجِبُكَ مِن أبِي تَمِيمٍ؟ يَرْكَعُ رَكْعتَيْنِ قَبْلَ صَلَاةِ المَغْرِبِ! فَقالَ عُقْبَةُ: إنَّا كُنَّا نَفْعَلُهُ علَى عَهْدِ رَسولِ اللَّهِ صلَّى اللهُ عليه وسلَّمَ، قُلتُ: فَما يَمْنَعُكَ الآنَ؟ قالَ: الشُّغْلُ.' فِي الحَيَاةِ اليَوْمِيَّةِ؟",
        "answer": "يُمكِنُ تَطْبِيقُ الحَدِيثِ فِي الحَيَاةِ اليَوْمِيَّةِ بِالإِقْبَالِ عَلَى صَلَاةِ الرَّكْعَتَيْنِ قَبْلَ المَغْرِبِ، وَالاجْتِهَادِ فِي أَدَاءِ النَّوَافِلِ لِتَكْمِيلِ الفَرَائِضِ وَالتَّقَرُّبِ إِلَى اللهِ تَعَالَى، مَعَ مُرَاعَاةِ عَدَمِ التَّشْدِيدِ عَلَى النَّفْسِ فِي حَالِ الانْشِغَالِ."
      },
      {
        "question": "مَا أَهَمِّيَّةُ الحَدِيثِ'سَمِعْتُ مَرْثَدَ بنَ عبدِ اللَّهِ اليَزَنِيَّ، قالَ: أتَيْتُ عُقْبَةَ بنَ عَامِرٍ الجُهَنِيَّ، فَقُلتُ: ألَا أُعْجِبُكَ مِن أبِي تَمِيمٍ؟ يَرْكَعُ رَكْعتَيْنِ قَبْلَ صَلَاةِ المَغْرِبِ! فَقالَ عُقْبَةُ: إنَّا كُنَّا نَفْعَلُهُ علَى عَهْدِ رَسولِ اللَّهِ صلَّى اللهُ عليه وسلَّمَ، قُلتُ: فَما يَمْنَعُكَ الآنَ؟ قالَ: الشُّغْلُ.' فِي الفِقْهِ الإِسْلَامِيِّ؟",
        "answer": "لِلحَدِيثِ أَهَمِّيَّةٌ فِي الفِقْهِ الإِسْلَامِيِّ؛ حَيْثُ يُثْبِتُ مَشْرُوعِيَّةَ صَلَاةِ النَّافِلَةِ قَبْلَ المَغْرِبِ، وَيُبَيِّنُ أَنَّهَا لَيْسَتْ بِوَاجِبَةٍ بَلْ مُسْتَحَبَّةٌ، وَأَنَّهَا مِنَ السُّنَنِ الَّتِي كَانَ يَفْعَلُهَا الصَّحَابَةُ رَضِيَ اللهُ عَنْهُمْ."
      },
      {
        "question": "مَا سَبَبُ وُرُودِ الحَدِيثِ'سَمِعْتُ مَرْثَدَ بنَ عبدِ اللَّهِ اليَزَنِيَّ، قالَ: أتَيْتُ عُقْبَةَ بنَ عَامِرٍ الجُهَنِيَّ، فَقُلتُ: ألَا أُعْجِبُكَ مِن أبِي تَمِيمٍ؟ يَرْكَعُ رَكْعتَيْنِ قَبْلَ صَلَاةِ المَغْرِبِ! فَقالَ عُقْبَةُ: إنَّا كُنَّا نَفْعَلُهُ علَى عَهْدِ رَسولِ اللَّهِ صلَّى اللهُ عليه وسلَّمَ، قُلتُ: فَما يَمْنَعُكَ الآنَ؟ قالَ: الشُّغْلُ.'؟",
        "answer": "سَبَبُ رِوَايَةِ الحَدِيثِ هُوَ بَيَانُ حُكْمِ صَلَاةِ الرَّكْعَتَيْنِ قَبْلَ المَغْرِبِ، وَتَأْكِيدُ أَنَّهَا مِنَ السُّنَنِ الَّتِي كَانَتْ مَشْهُورَةً فِي عَهْدِ النَّبِيِّ صَلَّى اللهُ عَلَيْهِ وَسَلَّمَ، وَأَنَّ الانْشِغَالَ قَدْ يَمْنَعُ مِنَ القِيَامِ بِهَا دُونَ نَفْيِ مَشْرُوعِيَّتِهَا."
      }
    ]
  }
]