[
  {
    "hadith_id": "1756",
    "hadith": "أنَّ النبيَّ صلَّى اللهُ عليه وسلَّمَ صَلَّى الظُّهْرَ والعَصْرَ، والمَغْرِبَ والعِشَاءَ، ثُمَّ رَقَدَ رَقْدَةً بالمُحَصَّبِ، ثُمَّ رَكِبَ إلى البَيْتِ، فَطَافَ بهِ.",
    "rawi": "أنس بن مالك",
    "mohdith": "البخاري",
    "book": "صحيح البخاري",
    "numberOrPage": "1756",
    "grade": "[صحيح]",
    "takhrij": "من أفراد البخاري على مسلم",
    "sharh": "الحَجُّ هو الرُّكنُ الخامِسُ مِن أركانِ الإسلامِ، وقد بيَّنَ رَسولُ اللهِ صلَّى اللهُ عليه وسلَّمَ مَناسِكَ الحجِّ بأقوالِه وأفعالِه، ونَقَلَها لنا الصَّحابةُ الكرامُ رَضيَ اللهُ عنهم أجمَعينَ.\r\nوفي هذا الحَديثِ يَحكي أنسُ بنُ مالكٍ رَضيَ اللهُ عنه جانبًا مِن هَدْيِ رَسولِ اللهِ صلَّى اللهُ عليه وسلَّمَ في حَجَّةِ الوَداعِ التي كانتْ في السَّنةِ العاشرةِ مِن الهِجرةِ، فذكَرَ أنَّ النبيَّ صلَّى اللهُ عليه وسلَّمَ صلَّى الظُّهرَ والعَصرَ، والمغربَ والعِشاءَ بِالمُحَصَّبِ، وهو مَكانٌ متَّسِعٌ بَينَ مكَّةَ ومِنًى، ويسمى خَيْفَ بَني كِنانةَ، وهو مَوجودٌ الآنَ في أوائلِ مكَّةَ في ما يُسمَّى قصْرَ السَّقافِ.\r\nثُمَّ نامَ صلَّى اللهُ عليه وسلَّمَ نَومةً خَفيفةً، وكان ذلك بَعْدَ أنْ رَمَى الجِمارَ، ونَفَرَ مِن مِنًى، ثُمَّ رَكِبَ مِن المُحصَّبِ مُتوجِّهًا إلى البيتِ، فطافَ به طَوافَ الوداعِ، وهو الطَّوافُ الأخيرُ الذي يكونُ مِن الحاجِّ قبْلَ مُغادرتِه مكَّةَ. \r\nوقدِ اختُلِفَ في سَببِ نُزولِ النبيِّ صلَّى اللهُ عليه وسلَّمَ المُحصَّبَ؛ فقيل: نَزَلَ فيه نُزولًا تابعًا للنُّسكِ، وإنَّه سُنَّةٌ، كما كان يَرى عبدُ اللهِ بنُ عمَرَ رَضيَ اللهُ عنهما، ورَوى أبو داودَ -وأصلُه في الصَّحيحَينِ- قالتْ عائشةُ رَضيَ اللهُ عنها: «إنَّما نَزَل رَسولُ اللهِ صلَّى اللهُ عليه وسلَّمَ المُحصَّبَ؛ لِيَكونَ أسمَحَ لِخُروجِه، وليسَ بسُنَّةٍ، فمَن شاء نزَلَه، ومَن شاء لم يَنزِلْه».",
    "hadith_lessons": [
      "يُستَفادُ مِنَ الحَدِيثِ'أنَّ النبيَّ صلَّى اللهُ عليه وسلَّمَ صَلَّى الظُّهْرَ والعَصْرَ، والمَغْرِبَ والعِشَاءَ، ثُمَّ رَقَدَ رَقْدَةً بالمُحَصَّبِ، ثُمَّ رَكِبَ إلى البَيْتِ، فَطَافَ بهِ.' عِدَّةُ دُرُوسٍ وَفَوَائِدَ، مِنْهَا: بَيَانُ هَدْيِ النَّبِيِّ صَلَّى اللهُ عَلَيْهِ وَسَلَّمَ فِي حَجَّةِ الوَدَاعِ، وَتَعْلِيمُ الصَّحَابَةِ مَنَاسِكَ الحَجِّ بِالفِعْلِ، وَمَشْرُوعِيَّةُ الجَمْعِ بَيْنَ الصَّلَوَاتِ فِي الحَجِّ لِلتَّيْسِيرِ عَلَى الحُجَّاجِ، وَمَشْرُوعِيَّةُ النَّزُولِ بِالمُحَصَّبِ بَعْدَ النَّفْرِ مِنْ مِنًى، وَطَوَافُ الوَدَاعِ قَبْلَ مُغَادَرَةِ مَكَّةَ."
    ],
    "hadith_application": [
      "يُمكِنُ تَطْبِيقُ الحَدِيثِ'أنَّ النبيَّ صلَّى اللهُ عليه وسلَّمَ صَلَّى الظُّهْرَ والعَصْرَ، والمَغْرِبَ والعِشَاءَ، ثُمَّ رَقَدَ رَقْدَةً بالمُحَصَّبِ، ثُمَّ رَكِبَ إلى البَيْتِ، فَطَافَ بهِ.' فِي الحَيَاةِ اليَوْمِيَّةِ بِاتِّبَاعِ سُنَّةِ النَّبِيِّ صَلَّى اللهُ عَلَيْهِ وَسَلَّمَ فِي الحَجِّ، وَالجَمْعِ بَيْنَ الصَّلَوَاتِ فِي المَوَاقِفِ الَّتِي تَتَطَلَّبُ التَّيْسِيرَ، وَالتَّرْكِيزِ عَلَى أَهَمِّيَّةِ طَوَافِ الوَدَاعِ كَخُتْمَةٍ لِمَنَاسِكَ الحَجِّ، وَالِاقْتِدَاءِ بِالنَّبِيِّ فِي النَّزُولِ بِالمُحَصَّبِ أَوْ تَرْكِهِ حَسَبَ التَّيْسِيرِ."
    ],
    "FT_Pairs": [
      {
        "question": "مَا هِيَ الرَّسَائِلُ الرَّئِيسِيَّةُ وَالدُّرُوسُ المُسْتَفَادَةُ والفَوَائِد المُستَخلصَة مِنَ الحَدِيثِ'أنَّ النبيَّ صلَّى اللهُ عليه وسلَّمَ صَلَّى الظُّهْرَ والعَصْرَ، والمَغْرِبَ والعِشَاءَ، ثُمَّ رَقَدَ رَقْدَةً بالمُحَصَّبِ، ثُمَّ رَكِبَ إلى البَيْتِ، فَطَافَ بهِ.'؟",
        "answer": "يُستَفادُ مِنَ الحَدِيثِ عِدَّةُ دُرُوسٍ وَفَوَائِدَ، مِنْهَا: بَيَانُ هَدْيِ النَّبِيِّ صَلَّى اللهُ عَلَيْهِ وَسَلَّمَ فِي حَجَّةِ الوَدَاعِ، وَتَعْلِيمُ الصَّحَابَةِ مَنَاسِكَ الحَجِّ بِالفِعْلِ، وَمَشْرُوعِيَّةُ الجَمْعِ بَيْنَ الصَّلَوَاتِ فِي الحَجِّ لِلتَّيْسِيرِ عَلَى الحُجَّاجِ، وَمَشْرُوعِيَّةُ النَّزُولِ بِالمُحَصَّبِ بَعْدَ النَّفْرِ مِنْ مِنًى، وَطَوَافُ الوَدَاعِ قَبْلَ مُغَادَرَةِ مَكَّةَ."
      },
      {
        "question": "كَيْفَ يُمْكِنُ تَطْبِيقُ الحَدِيثِ'أنَّ النبيَّ صلَّى اللهُ عليه وسلَّمَ صَلَّى الظُّهْرَ والعَصْرَ، والمَغْرِبَ والعِشَاءَ، ثُمَّ رَقَدَ رَقْدَةً بالمُحَصَّبِ، ثُمَّ رَكِبَ إلى البَيْتِ، فَطَافَ بهِ.' فِي الحَيَاةِ اليَوْمِيَّةِ؟",
        "answer": "يُمكِنُ تَطْبِيقُ الحَدِيثِ فِي الحَيَاةِ اليَوْمِيَّةِ بِاتِّبَاعِ سُنَّةِ النَّبِيِّ صَلَّى اللهُ عَلَيْهِ وَسَلَّمَ فِي الحَجِّ، وَالجَمْعِ بَيْنَ الصَّلَوَاتِ فِي المَوَاقِفِ الَّتِي تَتَطَلَّبُ التَّيْسِيرَ، وَالتَّرْكِيزِ عَلَى أَهَمِّيَّةِ طَوَافِ الوَدَاعِ كَخُتْمَةٍ لِمَنَاسِكَ الحَجِّ، وَالِاقْتِدَاءِ بِالنَّبِيِّ فِي النَّزُولِ بِالمُحَصَّبِ أَوْ تَرْكِهِ حَسَبَ التَّيْسِيرِ."
      },
      {
        "question": "مَا أَهَمِّيَّةُ الحَدِيثِ'أنَّ النبيَّ صلَّى اللهُ عليه وسلَّمَ صَلَّى الظُّهْرَ والعَصْرَ، والمَغْرِبَ والعِشَاءَ، ثُمَّ رَقَدَ رَقْدَةً بالمُحَصَّبِ، ثُمَّ رَكِبَ إلى البَيْتِ، فَطَافَ بهِ.' فِي الفِقْهِ الإِسْلَامِيِّ؟",
        "answer": "لِلحَدِيثِ أَهَمِّيَّةٌ كَبِيرَةٌ فِي الفِقْهِ الإِسْلَامِيِّ؛ حَيْثُ يُبَيِّنُ جُزْءًا مِنْ مَنَاسِكَ الحَجِّ، وَيُثْبِتُ مَشْرُوعِيَّةَ الجَمْعِ بَيْنَ الصَّلَوَاتِ فِي الحَجِّ، وَيُفِيدُ فِي الخِلَافِ الفِقْهِيِّ حَوْلَ سُنِّيَّةِ النَّزُولِ بِالمُحَصَّبِ، وَيُؤَكِّدُ عَلَى أَهَمِّيَّةِ طَوَافِ الوَدَاعِ كَرُكْنٍ مِنْ أَرْكَانِ الحَجِّ."
      },
      {
        "question": "مَا سَبَبُ وُرُودِ الحَدِيثِ'أنَّ النبيَّ صلَّى اللهُ عليه وسلَّمَ صَلَّى الظُّهْرَ والعَصْرَ، والمَغْرِبَ والعِشَاءَ، ثُمَّ رَقَدَ رَقْدَةً بالمُحَصَّبِ، ثُمَّ رَكِبَ إلى البَيْتِ، فَطَافَ بهِ.'؟",
        "answer": "سَبَبُ رِوَايَةِ الحَدِيثِ هُوَ بَيَانُ هَدْيِ النَّبِيِّ صَلَّى اللهُ عَلَيْهِ وَسَلَّمَ فِي حَجَّةِ الوَدَاعِ، وَتَعْلِيمُ الصَّحَابَةِ وَالمُسْلِمِينَ مَنَاسِكَ الحَجِّ بِالتَّفْصِيلِ. وَقَدِ اخْتُلِفَ فِي سَبَبِ نُزُولِ النَّبِيِّ بِالمُحَصَّبِ؛ فَمِنْهُمْ مَنْ رَأَى أَنَّهُ سُنَّةٌ، وَمِنْهُمْ مَنْ رَأَى أَنَّهُ لِلتَّيْسِيرِ فَقَطْ وَلَيْسَ بِسُنَّةٍ."
      }
    ]
  }
]